neurofly/__init__.py
neurofly/aug_segs.py
neurofly/common.py
neurofly/dbio.py
neurofly/image_reader.py
neurofly/interp_edges.py
neurofly/napari.yaml
neurofly/neurites.py
neurofly/patch.py
neurofly/seger.py
neurofly/segs_annotator.py
neurofly/simple_viewer.py
neurofly/skel_annotator.py
neurofly/vis.py
neurofly/models/__init__.py
neurofly/models/mpcn_dumpy.pth
neurofly/models/mpcn_tinygrad.py
neurofly/models/mpcn_torch.py
neurofly/models/next_pos.pth
neurofly/models/twoway_transformer.py
neurofly/models/unet_tinygrad.py
neurofly/models/unet_torch.py
neurofly/models/universal_tiny.pth
neurofly/neurodb/__init__.py
neurofly/neurodb/neurodb.py
neurofly/neurodb/sqliteDBIO.py
neurofly-0.1.4.dist-info/licenses/LICENSE
neurofly-0.1.4.dist-info/METADATA
neurofly-0.1.4.dist-info/WHEEL
neurofly-0.1.4.dist-info/entry_points.txt
neurofly-0.1.4.dist-info/top_level.txt
neurofly-0.1.4.dist-info/RECORD
