Metadata-Version: 2.4
Name: neurofly
Version: 0.1.4
Summary: A framework to annotate single neurons at whole-brain scale
Author-email: Rubin Zhao <beanli161514@gmail.com>
License: GPL-3.0-or-later
Project-URL: Homepage, https://github.com/beanli161514/neurofly
Classifier: Framework :: napari
Classifier: Programming Language :: Python :: 3
Requires-Python: >=3.8
License-File: LICENSE
Requires-Dist: PyQt5
Requires-Dist: napari
Requires-Dist: Rtree
Requires-Dist: networkx
Requires-Dist: tqdm
Requires-Dist: magicgui
Requires-Dist: brightest-path-lib
Requires-Dist: tifffile
Requires-Dist: scikit-image
Requires-Dist: scipy
Requires-Dist: torch
Requires-Dist: tinygrad>=0.9.2
Requires-Dist: pathlib
Requires-Dist: h5py
Requires-Dist: zarr
Dynamic: license-file
